{
    "key": "group_652d52e238d4d",
    "title": "Component : Download Form",
    "fields": [
        {
            "key": "field_652d52e2b5b62",
            "label": "Image",
            "name": "download_form",
            "aria-label": "",
            "type": "clone",
            "instructions": "",
            "required": 0,
            "conditional_logic": 0,
            "wrapper": {
                "width": "",
                "class": "",
                "id": ""
            },
            "documentation_notes": "",
            "clone": [
                "group_5f5c43d8cb8ad"
            ],
            "display": "seamless",
            "layout": "block",
            "prefix_label": 0,
            "prefix_name": 1
        },
        {
            "key": "field_652d5322b5b63",
            "label": "Heading",
            "name": "download_form",
            "aria-label": "",
            "type": "clone",
            "instructions": "",
            "required": 0,
            "conditional_logic": 0,
            "wrapper": {
                "width": "",
                "class": "",
                "id": ""
            },
            "documentation_notes": "",
            "clone": [
                "group_5f592cd62e1bc"
            ],
            "display": "seamless",
            "layout": "block",
            "prefix_label": 0,
            "prefix_name": 1
        },
        {
            "key": "field_652d5342b5b64",
            "label": "Description",
            "name": "download_form_description",
            "aria-label": "",
            "type": "textarea",
            "instructions": "",
            "required": 0,
            "conditional_logic": 0,
            "wrapper": {
                "width": "",
                "class": "",
                "id": ""
            },
            "documentation_notes": "",
            "default_value": "",
            "maxlength": "",
            "rows": "",
            "placeholder": "",
            "new_lines": ""
        },
        {
            "key": "field_652d558ab5b65",
            "label": "Form",
            "name": "download_form_form_id",
            "aria-label": "",
            "type": "select",
            "instructions": "",
            "required": 0,
            "conditional_logic": 0,
            "wrapper": {
                "width": "",
                "class": "",
                "id": ""
            },
            "documentation_notes": "",
            "choices": {
                "1": "Contact",
                "4": "Contact Barb",
                "2": "Event Registration - Free",
                "3": "Event Registration - Paid"
            },
            "default_value": false,
            "return_format": "value",
            "multiple": 0,
            "allow_null": 0,
            "ui": 0,
            "ajax": 0,
            "placeholder": ""
        }
    ],
    "location": [
        [
            {
                "param": "component",
                "operator": "==",
                "value": "download-form"
            }
        ]
    ],
    "menu_order": 0,
    "position": "normal",
    "style": "default",
    "label_placement": "top",
    "instruction_placement": "label",
    "hide_on_screen": "",
    "active": true,
    "description": "",
    "show_in_rest": 0,
    "modified": 1697469853
}
